README.md
README.rst
setup.py
pygarl/__init__.py
pygarl/__main__.py
pygarl/abstracts.py
pygarl/base.py
pygarl/classifiers.py
pygarl/data_readers.py
pygarl/middlewares.py
pygarl/mocks.py
pygarl/predictors.py
pygarl/recorders.py
pygarl/sample_managers.py
pygarl/utils.py
pygarl.egg-info/PKG-INFO
pygarl.egg-info/SOURCES.txt
pygarl.egg-info/dependency_links.txt
pygarl.egg-info/entry_points.txt
pygarl.egg-info/requires.txt
pygarl.egg-info/top_level.txt
pygarl/examples/__init__.py
pygarl/examples/discrete_sample_manager.py
pygarl/examples/finger_sensor.py
pygarl/examples/gesture_keyboard.py
pygarl/examples/gradient_threshold.py
pygarl/examples/gradient_threshold_piezo.py
pygarl/examples/highest_axis_predictor.py
pygarl/examples/knock_sensor.py
pygarl/examples/mlpclassifier.py
pygarl/examples/piezo_sensor.py
pygarl/examples/plot_sample.py
pygarl/examples/plot_sample_from_file.py
pygarl/examples/plot_sample_stream_file.py
pygarl/examples/serial_data_reader.py
pygarl/examples/stream_sample_manager.py
pygarl/examples/svmclassifier.py
pygarl/plugins/__init__.py
pygarl/plugins/plist.py
pygarl/plugins/plot.py
pygarl/plugins/record.py
pygarl/plugins/sprint.py
pygarl/plugins/train.py
pygarl/plugins/trainers/__init__.py
pygarl/plugins/trainers/finger_trainer.py
pygarl/plugins/trainers/knock_trainer.py
pygarl/plugins/trainers/piezo_trainer.py
pygarl/tests/__init__.py
pygarl/tests/test_abstracts.py
pygarl/tests/test_base.py
pygarl/tests/test_classifiers.py
pygarl/tests/test_predictors.py
pygarl/tests/test_recorders.py
pygarl/tests/test_sample_managers.py